odoo8_addon_product_online_category-8.0.1.0.0.99.dev3-py3.8-nspkg.pth
odoo_addons/product_online_category/README.rst
odoo_addons/product_online_category/__init__.py
odoo_addons/product_online_category/__openerp__.py
odoo_addons/product_online_category/models/__init__.py
odoo_addons/product_online_category/models/product.py
odoo8_addon_product_online_category-8.0.1.0.0.99.dev3.dist-info/METADATA
odoo8_addon_product_online_category-8.0.1.0.0.99.dev3.dist-info/WHEEL
odoo8_addon_product_online_category-8.0.1.0.0.99.dev3.dist-info/namespace_packages.txt
odoo8_addon_product_online_category-8.0.1.0.0.99.dev3.dist-info/top_level.txt
odoo8_addon_product_online_category-8.0.1.0.0.99.dev3.dist-info/RECORD
